Metadata-Version: 2.1
Name: mikrotik-bt5
Version: 1.0.0
Summary: MikroTik BT5 scanner
Home-page: https://github.com/Anrijs/MikroTik-BT5-Python
Classifier: Programming Language :: Python
Classifier: Programming Language :: Python :: 3
Classifier: License :: OSI Approved :: MIT License
Classifier: Operating System :: OS Independent
